{"updated_at":"2026-04-24T21:30:38.463651","province":"경기","district":"안산시","data":[{"gmgoCd":"3949","name":"안산중앙(본점)","province":"경기","district":"안산시","disclosure":{"evaluation_date":"20251231","grade":"2","bis_ratio":11.85,"dividend_rate":2.0},"products":{"온라인자립예탁금":{"0":{"r":0.05,"s":"w"}},"상상모바일통장":{"0":{"r":0.04,"s":"m"}}}},{"gmgoCd":"3904","name":"신반월(본점)","province":"경기","district":"안산시","disclosure":{"evaluation_date":"20251231","grade":"3","bis_ratio":19.76,"dividend_rate":2.0},"products":{"온라인자립예탁금":{"0":{"r":0.05,"s":"w"}},"상상모바일통장":{"0":{"r":0.1,"s":"m"}}}},{"gmgoCd":"3902","name":"안산동부(본점)","province":"경기","district":"안산시","disclosure":{"evaluation_date":"20251231","grade":"2","bis_ratio":13.28,"dividend_rate":4.0},"products":{"온라인자립예탁금":{"0":{"r":0.05,"s":"w"}},"상상모바일통장":{"0":{"r":0.1,"s":"m"}}}},{"gmgoCd":"3903","name":"군자(본점)","province":"경기","district":"안산시","disclosure":{"evaluation_date":"20251231","grade":"1","bis_ratio":24.43,"dividend_rate":4.0},"products":{"온라인자립예탁금":{"0":{"r":0.05,"s":"w"}},"상상모바일통장":{"0":{"r":0.1,"s":"m"}}}}]}