{"updated_at":"2026-04-19T10:29:38.774655","province":"서울","district":"종로구","data":[{"gmgoCd":"0113","name":"대학로(본점)","province":"서울","district":"종로구","disclosure":{"evaluation_date":"20251231","grade":"3","bis_ratio":5.52,"dividend_rate":0.0},"products":{"온라인자립예탁금":{"0":{"r":0.1,"s":"w"}}}},{"gmgoCd":"0109","name":"종로3.4가(본점)","province":"서울","district":"종로구","disclosure":{"evaluation_date":"20251231","grade":"2","bis_ratio":-0.02,"dividend_rate":0.0},"products":{"온라인자립예탁금":{"0":{"r":0.1,"s":"w"}},"상상모바일통장":{"0":{"r":0.1,"s":"m"}}}},{"gmgoCd":"0142","name":"종로광장(본점)","province":"서울","district":"종로구","disclosure":{"evaluation_date":"20251231","grade":"2","bis_ratio":15.54,"dividend_rate":2.4966},"products":{"온라인자립예탁금":{"0":{"r":0.1,"s":"w"}},"상상모바일통장":{"0":{"r":0.1,"s":"m"}}}},{"gmgoCd":"0141","name":"종로중부(본점)","province":"서울","district":"종로구","disclosure":{"evaluation_date":"20251231","grade":"2","bis_ratio":16.34,"dividend_rate":3.1},"products":{"온라인자립예탁금":{"0":{"r":0.1,"s":"w"}},"상상모바일통장":{"0":{"r":0.1,"s":"m"}}}},{"gmgoCd":"0137","name":"동대문상가(본점)","province":"서울","district":"종로구","disclosure":{"evaluation_date":"20251231","grade":"2","bis_ratio":22.62,"dividend_rate":2.96575},"products":{"온라인자립예탁금":{"0":{"r":0.1,"s":"w"}},"상상모바일통장":{"0":{"r":0.1,"s":"m"}}}},{"gmgoCd":"0102","name":"광화문(본점)","province":"서울","district":"종로구","disclosure":{"evaluation_date":"20251231","grade":"3","bis_ratio":8.46,"dividend_rate":0.0},"products":{"온라인자립예탁금":{"0":{"r":0.2,"s":"w"}},"상상모바일통장":{"0":{"r":0.1,"s":"m"}}}},{"gmgoCd":"0106","name":"종로서부(본점)","province":"서울","district":"종로구","disclosure":{"evaluation_date":"20251231","grade":"3","bis_ratio":8.47,"dividend_rate":0.0},"products":{"온라인자립예탁금":{"0":{"r":0.2,"s":"w"}},"상상모바일통장":{"0":{"r":0.1,"s":"m"}}}},{"gmgoCd":"0104","name":"삼청(본점)","province":"서울","district":"종로구","disclosure":{"evaluation_date":"20251231","grade":"3","bis_ratio":16.84,"dividend_rate":2.5},"products":{"온라인자립예탁금":{"0":{"r":0.2,"s":"w"}},"상상모바일통장":{"0":{"r":0.2,"s":"m"}}}},{"gmgoCd":"0107","name":"교남동(본점)","province":"서울","district":"종로구","disclosure":{"evaluation_date":"20251231","grade":"2","bis_ratio":13.03,"dividend_rate":3.02001},"products":{"온라인자립예탁금":{"0":{"r":0.1,"s":"w"}},"상상모바일통장":{"0":{"r":0.2,"s":"m"}}}},{"gmgoCd":"0101","name":"청운효자동(본점)","province":"서울","district":"종로구","disclosure":{"evaluation_date":"20251231","grade":"2","bis_ratio":13.61,"dividend_rate":3.6},"products":{"온라인자립예탁금":{"0":{"r":0.2,"s":"w"}},"상상모바일통장":{"0":{"r":0.1,"s":"m"}}}},{"gmgoCd":"0121","name":"종로숭인(본점)","province":"서울","district":"종로구","disclosure":{"evaluation_date":"20251231","grade":"2","bis_ratio":15.74,"dividend_rate":3.00334},"products":{"온라인자립예탁금":{"0":{"r":0.2,"s":"w"}},"상상모바일통장":{"0":{"r":0.1,"s":"m"}}}},{"gmgoCd":"0119","name":"종로동부(본점)","province":"서울","district":"종로구","disclosure":{"evaluation_date":"20251231","grade":"2","bis_ratio":17.28,"dividend_rate":2.8},"products":{"온라인자립예탁금":{"0":{"r":0.2,"s":"w"}},"상상모바일통장":{"0":{"r":0.1,"s":"m"}}}},{"gmgoCd":"0122","name":"강북삼성병원(본점)","province":"서울","district":"종로구","disclosure":{"evaluation_date":"20251231","grade":"2","bis_ratio":236.17,"dividend_rate":3.50029},"products":{"온라인자립예탁금":{"0":{"r":0.2,"s":"w"}}}},{"gmgoCd":"0116","name":"명륜(본점)","province":"서울","district":"종로구","disclosure":{"evaluation_date":"20251231","grade":"3","bis_ratio":12.23,"dividend_rate":1.99999},"products":{"온라인자립예탁금":{"0":{"r":0.2,"s":"w"}},"상상모바일통장":{"0":{"r":0.3,"s":"m"}}}},{"gmgoCd":"0105","name":"세검정(본점)","province":"서울","district":"종로구","disclosure":{"evaluation_date":"20251231","grade":"2","bis_ratio":9.34,"dividend_rate":0.0},"products":{"온라인자립예탁금":{"0":{"r":0.5,"s":"w"}},"상상모바일통장":{"0":{"r":0.1,"s":"m"}}}},{"gmgoCd":"0103","name":"사직동(본점)","province":"서울","district":"종로구","disclosure":{"evaluation_date":"20251231","grade":"2","bis_ratio":24.84,"dividend_rate":3.20105},"products":{"온라인자립예탁금":{"0":{"r":0.1,"s":"w"}},"상상모바일통장":{"0":{"r":1.0,"s":"m"}}}},{"gmgoCd":"0108","name":"인사동길(본점)","province":"서울","district":"종로구","disclosure":{"evaluation_date":"20251231","grade":"3","bis_ratio":6.52,"dividend_rate":0.0},"products":{"온라인자립예탁금":{"0":{"r":0.01,"s":"w"}},"상상모바일통장":{"0":{"r":2.0,"s":"m"}}}},{"gmgoCd":"0118","name":"종로중앙(본점)","province":"서울","district":"종로구","disclosure":{"evaluation_date":"20251231","grade":"3","bis_ratio":3.7,"dividend_rate":0.0},"products":{"온라인자립예탁금":{"0":{"r":0.2,"s":"w"}},"상상모바일통장":{"0":{"r":2.6,"s":"m"}}}}]}