{"updated_at":"2026-04-01T08:58:23.285976","province":"서울","district":"중구","data":[{"gmgoCd":"0215","name":"중림.만리(본점)","province":"서울","district":"중구","grade":"3","bis_ratio":12.46,"products":{"온라인자립예탁금":{"0":{"r":0.1,"s":"w"}},"상상모바일통장":{"0":{"r":2.4,"s":"m"}}}},{"gmgoCd":"0203","name":"회현동(본점)","province":"서울","district":"중구","grade":"3","bis_ratio":0.0,"products":{"온라인자립예탁금":{"0":{"r":0.1,"s":"w"}},"상상모바일통장":{"0":{"r":0.1,"s":"m"}}}},{"gmgoCd":"0204","name":"명동(본점)","province":"서울","district":"중구","grade":"3","bis_ratio":7.67,"products":{"온라인자립예탁금":{"0":{"r":0.1,"s":"w"}},"상상모바일통장":{"0":{"r":0.1,"s":"m"}}}},{"gmgoCd":"0224","name":"롯데쇼핑(본점)","province":"서울","district":"중구","grade":"1","bis_ratio":276.36,"products":{"상상모바일통장":{"0":{"r":0.1,"s":"w"}}}},{"gmgoCd":"0206","name":"필동(본점)","province":"서울","district":"중구","grade":"2","bis_ratio":12.6,"products":{"온라인자립예탁금":{"0":{"r":0.1,"s":"w"}},"상상모바일통장":{"0":{"r":0.1,"s":"m"}}}},{"gmgoCd":"0233","name":"호텔신라(본점)","province":"서울","district":"중구","grade":"1","bis_ratio":524.6,"products":{"온라인자립예탁금":{"0":{"r":0.1,"s":"w"}}}},{"gmgoCd":"0208","name":"신당1.2.3동(본점)","province":"서울","district":"중구","grade":"2","bis_ratio":17.52,"products":{"온라인자립예탁금":{"0":{"r":0.1,"s":"w"}},"상상모바일통장":{"0":{"r":0.1,"s":"m"}}}},{"gmgoCd":"0250","name":"평화(본점)","province":"서울","district":"중구","grade":"3","bis_ratio":8.41,"products":{"온라인자립예탁금":{"0":{"r":0.1,"s":"w"}},"상상모바일통장":{"0":{"r":0.1,"s":"m"}}}},{"gmgoCd":"0213","name":"신중앙(본점)","province":"서울","district":"중구","grade":"2","bis_ratio":13.39,"products":{"온라인자립예탁금":{"0":{"r":0.01,"s":"w"}},"상상모바일통장":{"0":{"r":0.1,"s":"m"}}}},{"gmgoCd":"0252","name":"청계(본점)","province":"서울","district":"중구","grade":"2","bis_ratio":5.71,"products":{"온라인자립예탁금":{"0":{"r":0.1,"s":"w"}},"상상모바일통장":{"0":{"r":0.1,"s":"m"}}}},{"gmgoCd":"0325","name":"씨제이제일제당(본점)","province":"서울","district":"중구","grade":"1","bis_ratio":33.87,"products":{"온라인자립예탁금":{"0":{"r":0.1,"s":"w"}},"상상모바일통장":{"0":{"r":0.05,"s":"w"}}}},{"gmgoCd":"0254","name":"남대문(본점)","province":"서울","district":"중구","grade":"2","bis_ratio":14.82,"products":{"온라인자립예탁금":{"0":{"r":0.1,"s":"w"}},"상상모바일통장":{"0":{"r":0.1,"s":"m"}}}},{"gmgoCd":"0212","name":"동화동(본점)","province":"서울","district":"중구","grade":"3","bis_ratio":8.7,"products":{"온라인자립예탁금":{"0":{"r":0.01,"s":"w"}},"상상모바일통장":{"0":{"r":0.01,"s":"m"}}}}]}