{
  "updated_at": "2026-04-01T03:16:22+09:00",
  "gmgoCd": "0536",
  "name": "망우동",
  "meta": {
    "head_office": {
      "name": "망우동(본점)",
      "address": "서울 중랑구 망우로 481",
      "phone": "02-433-9891",
      "province": "서울",
      "district": "중랑구"
    },
    "branches": []
  },
  "rates": {
    "deposit": {
      "MG더뱅킹정기예금": {
        "12": {
          "r": 3.09,
          "s": "w"
        }
      }
    },
    "saving": {
      "MG더뱅킹정기적금": {
        "6": {
          "r": 1.0,
          "s": "w"
        },
        "12": {
          "r": 2.8,
          "s": "w"
        }
      },
      "MG더뱅킹자유적금": {
        "12": {
          "r": 2.2,
          "s": "w"
        }
      }
    },
    "demand": {
      "온라인자립예탁금": {
        "0": {
          "r": 0.1,
          "s": "w"
        }
      },
      "상상모바일통장": {
        "0": {
          "r": 0.1,
          "s": "w"
        }
      }
    }
  },
  "top_picks": {
    "deposit": {
      "name": "MG더뱅킹정기예금",
      "month": "12",
      "r": 3.09,
      "s": "w"
    },
    "saving": {
      "name": "MG더뱅킹정기적금",
      "month": "12",
      "r": 2.8,
      "s": "w"
    }
  },
  "grades_history": [
    {
      "period": "2025_06",
      "grade": "3",
      "bis_ratio": "5.07"
    },
    {
      "period": "2024_12",
      "grade": "3",
      "bis_ratio": "9.45"
    },
    {
      "period": "2024_06",
      "grade": "3",
      "bis_ratio": "8.94"
    },
    {
      "period": "2023_12",
      "grade": "2",
      "bis_ratio": "9.09"
    }
  ],
  "nearby_branches": [
    {
      "gmgoCd": "0527",
      "name": "중랑서부",
      "province": "서울",
      "district": "중랑구"
    },
    {
      "gmgoCd": "0528",
      "name": "사가정",
      "province": "서울",
      "district": "중랑구"
    },
    {
      "gmgoCd": "0529",
      "name": "서울동부",
      "province": "서울",
      "district": "중랑구"
    },
    {
      "gmgoCd": "0530",
      "name": "용마",
      "province": "서울",
      "district": "중랑구"
    },
    {
      "gmgoCd": "0531",
      "name": "서울상봉",
      "province": "서울",
      "district": "중랑구"
    }
  ]
}