{
  "updated_at": "2026-04-06T14:29:40+09:00",
  "gmgoCd": "1520",
  "name": "범천2동",
  "meta": {
    "head_office": {
      "name": "범천2동(본점)",
      "address": "부산 부산진구 신암로 50",
      "phone": "051-645-5251",
      "province": "부산",
      "district": "부산진구"
    },
    "branches": []
  },
  "rates": {
    "deposit": {},
    "saving": {},
    "demand": {
      "온라인자립예탁금": {
        "0": {
          "r": 0.1,
          "s": "w"
        }
      },
      "상상모바일통장": {
        "0": {
          "r": 0.1,
          "s": "m"
        }
      }
    }
  },
  "top_picks": {
    "deposit": null,
    "saving": null
  },
  "disclosure_history": [
    {
      "evaluation_date": "20251231",
      "grade": "2",
      "bis_ratio": 15.06,
      "dividend_rate": 2.8
    },
    {
      "evaluation_date": "20250630",
      "grade": "2",
      "bis_ratio": 15.53,
      "dividend_rate": 3.40001
    },
    {
      "evaluation_date": "20241231",
      "grade": "2",
      "bis_ratio": 16.53,
      "dividend_rate": 3.40001
    },
    {
      "evaluation_date": "20240630",
      "grade": "2",
      "bis_ratio": 18.19,
      "dividend_rate": 4.50008
    },
    {
      "evaluation_date": "20231231",
      "grade": "2",
      "bis_ratio": 18.98,
      "dividend_rate": 4.50008
    }
  ],
  "nearby_branches": [
    {
      "gmgoCd": "1501",
      "name": "부전1동",
      "province": "부산",
      "district": "부산진구"
    },
    {
      "gmgoCd": "1502",
      "name": "서면",
      "province": "부산",
      "district": "부산진구"
    },
    {
      "gmgoCd": "1504",
      "name": "연지동",
      "province": "부산",
      "district": "부산진구"
    },
    {
      "gmgoCd": "1505",
      "name": "초읍동",
      "province": "부산",
      "district": "부산진구"
    },
    {
      "gmgoCd": "1506",
      "name": "시민공원",
      "province": "부산",
      "district": "부산진구"
    }
  ]
}