{
  "updated_at": "2026-04-25T10:30:42+09:00",
  "gmgoCd": "1608",
  "name": "사직2동",
  "meta": {
    "head_office": {
      "name": "사직2동(본점)",
      "address": "부산 동래구 사직북로47번길 47",
      "phone": "051-501-9633",
      "province": "부산",
      "district": "동래구"
    },
    "branches": []
  },
  "rates": {
    "deposit": {
      "MG더뱅킹정기예금": {
        "3": {
          "r": 0.7,
          "s": "m"
        },
        "6": {
          "r": 2.0,
          "s": "m"
        },
        "12": {
          "r": 2.8,
          "s": "m"
        }
      }
    },
    "saving": {
      "MG더뱅킹정기적금": {
        "6": {
          "r": 2.0,
          "s": "m"
        },
        "12": {
          "r": 2.5,
          "s": "m"
        }
      },
      "MG더뱅킹자유적금": {
        "12": {
          "r": 2.3,
          "s": "m"
        }
      }
    },
    "demand": {
      "온라인자립예탁금": {
        "0": {
          "r": 0.1,
          "s": "w"
        }
      },
      "상상모바일통장": {
        "0": {
          "r": 0.1,
          "s": "m"
        }
      }
    }
  },
  "top_picks": {
    "deposit": {
      "name": "MG더뱅킹정기예금",
      "month": "12",
      "r": 2.8,
      "s": "m"
    },
    "saving": {
      "name": "MG더뱅킹정기적금",
      "month": "12",
      "r": 2.5,
      "s": "m"
    }
  },
  "disclosure_history": [
    {
      "evaluation_date": "20251231",
      "grade": "2",
      "bis_ratio": 16.57,
      "dividend_rate": 0.67999
    },
    {
      "evaluation_date": "20241231",
      "grade": "3",
      "bis_ratio": 13.07,
      "dividend_rate": 0.0
    },
    {
      "evaluation_date": "20240630",
      "grade": "3",
      "bis_ratio": 13.13,
      "dividend_rate": 4.00001
    },
    {
      "evaluation_date": "20231231",
      "grade": "3",
      "bis_ratio": 15.7,
      "dividend_rate": 4.00001
    }
  ],
  "nearby_branches": [
    {
      "gmgoCd": "1601",
      "name": "수민동",
      "province": "부산",
      "district": "동래구"
    },
    {
      "gmgoCd": "1602",
      "name": "복산동",
      "province": "부산",
      "district": "동래구"
    },
    {
      "gmgoCd": "1603",
      "name": "명륜동",
      "province": "부산",
      "district": "동래구"
    },
    {
      "gmgoCd": "1605",
      "name": "온천",
      "province": "부산",
      "district": "동래구"
    },
    {
      "gmgoCd": "1606",
      "name": "온천3동",
      "province": "부산",
      "district": "동래구"
    }
  ]
}