{
  "updated_at": "2026-04-01T17:15:58+09:00",
  "gmgoCd": "2724",
  "name": "우주",
  "meta": {
    "head_office": {
      "name": "우주(본점)",
      "address": "전남 고흥군 과역면 고흥로 2985",
      "phone": "061-832-9534",
      "province": "전남",
      "district": "고흥군"
    },
    "branches": [
      {
        "name": "우주(동강)",
        "address": "전남 고흥군 동강면 고흥로 4268",
        "phone": "061-833-2456",
        "district": "고흥군"
      }
    ]
  },
  "rates": {
    "deposit": {
      "MG더뱅킹정기예금": {
        "3": {
          "r": 2.9,
          "s": "m"
        },
        "6": {
          "r": 3.2,
          "s": "m"
        },
        "12": {
          "r": 3.55,
          "s": "m"
        }
      }
    },
    "saving": {
      "MG더뱅킹정기적금": {
        "6": {
          "r": 3.0,
          "s": "m"
        },
        "12": {
          "r": 3.25,
          "s": "m"
        }
      },
      "MG더뱅킹자유적금": {
        "12": {
          "r": 2.86,
          "s": "m"
        }
      }
    },
    "demand": {
      "온라인자립예탁금": {
        "0": {
          "r": 0.2,
          "s": "w"
        }
      },
      "상상모바일통장": {
        "0": {
          "r": 0.2,
          "s": "m"
        }
      }
    }
  },
  "top_picks": {
    "deposit": {
      "name": "MG더뱅킹정기예금",
      "month": "12",
      "r": 3.55,
      "s": "m"
    },
    "saving": {
      "name": "MG더뱅킹정기적금",
      "month": "12",
      "r": 3.25,
      "s": "m"
    }
  },
  "grades_history": [
    {
      "period": "2025_12",
      "grade": "3",
      "bis_ratio": "5.87"
    },
    {
      "period": "2025_06",
      "grade": "3",
      "bis_ratio": "6.06"
    },
    {
      "period": "2024_12",
      "grade": "3",
      "bis_ratio": "7.36"
    },
    {
      "period": "2024_06",
      "grade": "3",
      "bis_ratio": "6.96"
    },
    {
      "period": "2023_12",
      "grade": "3",
      "bis_ratio": "7.18"
    }
  ],
  "nearby_branches": [
    {
      "gmgoCd": "2722",
      "name": "고흥",
      "province": "전남",
      "district": "고흥군"
    },
    {
      "gmgoCd": "2723",
      "name": "녹동",
      "province": "전남",
      "district": "고흥군"
    }
  ]
}