{
  "updated_at": "2026-03-30T15:58:01+09:00",
  "gmgoCd": "3206",
  "name": "천안서부",
  "meta": {
    "head_office": {
      "name": "천안서부(본점)",
      "address": "충남 천안시 동남구 서부대로 270",
      "phone": "041-574-6100",
      "province": "충남",
      "district": "천안시"
    },
    "branches": [
      {
        "name": "천안서부(쌍용)",
        "address": "충남 천안시 동남구 쌍용대로 70-3",
        "phone": "041-574-6103",
        "district": "천안시"
      },
      {
        "name": "천안서부(백석)",
        "address": "충남 천안시 서북구 백석로 93",
        "phone": "041-558-6101",
        "district": "천안시"
      },
      {
        "name": "천안서부(신방통정)",
        "address": "충남 천안시 동남구 통정5로 67",
        "phone": "041-578-6101",
        "district": "천안시"
      },
      {
        "name": "천안서부(봉명)",
        "address": "충남 천안시 동남구 봉정로 50",
        "phone": "041-574-6101",
        "district": "천안시"
      },
      {
        "name": "천안서부(신불당)",
        "address": "충남 천안시 서북구 불당26로 77",
        "phone": "041-577-6101",
        "district": "천안시"
      },
      {
        "name": "천안서부(불무)",
        "address": "충남 천안시 서북구 불당26로 144",
        "phone": "041-569-6101",
        "district": "천안시"
      },
      {
        "name": "천안서부(두정)",
        "address": "충남 천안시 서북구 천안대로 1018",
        "phone": "041-551-6101",
        "district": "천안시"
      }
    ]
  },
  "rates": {
    "deposit": {
      "MG더뱅킹정기예금": {
        "6": {
          "r": 2.7,
          "s": "m"
        },
        "12": {
          "r": 2.7,
          "s": "m"
        },
        "3": {
          "r": 0.0,
          "s": "m"
        }
      }
    },
    "saving": {
      "MG더뱅킹정기적금": {
        "6": {
          "r": 2.2,
          "s": "m"
        },
        "12": {
          "r": 2.7,
          "s": "m"
        }
      },
      "MG더뱅킹자유적금": {
        "12": {
          "r": 2.0,
          "s": "m"
        }
      }
    },
    "demand": {
      "온라인자립예탁금": {
        "0": {
          "r": 0.01,
          "s": "w"
        }
      },
      "상상모바일통장": {
        "0": {
          "r": 0.01,
          "s": "m"
        }
      }
    }
  },
  "top_picks": {
    "deposit": {
      "name": "MG더뱅킹정기예금",
      "month": "6",
      "r": 2.7,
      "s": "m"
    },
    "saving": {
      "name": "MG더뱅킹정기적금",
      "month": "12",
      "r": 2.7,
      "s": "m"
    }
  },
  "grades_history": [
    {
      "period": "2025_06",
      "grade": "3",
      "bis_ratio": "10.17"
    },
    {
      "period": "2024_12",
      "grade": "2",
      "bis_ratio": "11.08"
    },
    {
      "period": "2024_06",
      "grade": "2",
      "bis_ratio": "10.4"
    },
    {
      "period": "2023_12",
      "grade": "2",
      "bis_ratio": "9.15"
    }
  ],
  "nearby_branches": [
    {
      "gmgoCd": "3203",
      "name": "천안",
      "province": "충남",
      "district": "천안시"
    },
    {
      "gmgoCd": "3204",
      "name": "선영",
      "province": "충남",
      "district": "천안시"
    },
    {
      "gmgoCd": "3205",
      "name": "천안동부",
      "province": "충남",
      "district": "천안시"
    },
    {
      "gmgoCd": "3208",
      "name": "중부",
      "province": "충남",
      "district": "천안시"
    },
    {
      "gmgoCd": "3211",
      "name": "북천안",
      "province": "충남",
      "district": "천안시"
    }
  ]
}