{
  "updated_at": "2026-04-02T21:29:43+09:00",
  "gmgoCd": "4040",
  "name": "의정부중앙",
  "meta": {
    "head_office": {
      "name": "의정부중앙(본점)",
      "address": "경기 의정부시 시민로 53",
      "phone": "031-855-9400",
      "province": "경기",
      "district": "의정부시"
    },
    "branches": [
      {
        "name": "의정부중앙(제일시장)",
        "address": "경기 의정부시 태평로89번길 20-8",
        "phone": "031-845-9400",
        "district": "의정부시"
      },
      {
        "name": "의정부중앙(행복)",
        "address": "경기 의정부시 호국로1309번길 32",
        "phone": "031-843-9400",
        "district": "의정부시"
      },
      {
        "name": "의정부중앙(의정부역)",
        "address": "경기 의정부시 태평로 11",
        "phone": "031-855-3400",
        "district": "의정부시"
      },
      {
        "name": "의정부중앙(범골)",
        "address": "경기 의정부시 호동로 16",
        "phone": "031-879-5500",
        "district": "의정부시"
      }
    ]
  },
  "rates": {
    "deposit": {
      "MG더뱅킹정기예금": {
        "12": {
          "r": 2.6,
          "s": "m"
        }
      }
    },
    "saving": {
      "MG더뱅킹정기적금": {
        "12": {
          "r": 3.2,
          "s": "m"
        },
        "6": {
          "r": 0.0,
          "s": "m"
        }
      },
      "MG더뱅킹자유적금": {
        "12": {
          "r": 2.5,
          "s": "m"
        }
      }
    },
    "demand": {
      "온라인자립예탁금": {
        "0": {
          "r": 0.1,
          "s": "w"
        }
      },
      "상상모바일통장": {
        "0": {
          "r": 0.1,
          "s": "m"
        }
      }
    }
  },
  "top_picks": {
    "deposit": {
      "name": "MG더뱅킹정기예금",
      "month": "12",
      "r": 2.6,
      "s": "m"
    },
    "saving": {
      "name": "MG더뱅킹정기적금",
      "month": "12",
      "r": 3.2,
      "s": "m"
    }
  },
  "disclosure_history": [
    {
      "evaluation_date": "20251231",
      "grade": "2",
      "bis_ratio": 16.46,
      "dividend_rate": 3.0
    },
    {
      "evaluation_date": "20250630",
      "grade": "2",
      "bis_ratio": 13.95,
      "dividend_rate": 4.0
    },
    {
      "evaluation_date": "20241231",
      "grade": "2",
      "bis_ratio": 13.14,
      "dividend_rate": 4.0
    },
    {
      "evaluation_date": "20240630",
      "grade": "2",
      "bis_ratio": 11.35,
      "dividend_rate": 4.5
    },
    {
      "evaluation_date": "20231231",
      "grade": "2",
      "bis_ratio": 11.19,
      "dividend_rate": 4.5
    }
  ],
  "nearby_branches": [
    {
      "gmgoCd": "4007",
      "name": "호원",
      "province": "경기",
      "district": "의정부시"
    },
    {
      "gmgoCd": "4009",
      "name": "의정부신곡",
      "province": "경기",
      "district": "의정부시"
    },
    {
      "gmgoCd": "4014",
      "name": "의정부동부",
      "province": "경기",
      "district": "의정부시"
    },
    {
      "gmgoCd": "4042",
      "name": "의정부서부",
      "province": "경기",
      "district": "의정부시"
    }
  ]
}