{
  "updated_at": "2026-04-26T14:30:45+09:00",
  "gmgoCd": "4144",
  "name": "구리",
  "meta": {
    "head_office": {
      "name": "구리(본점)",
      "address": "경기 구리시 안골로 55",
      "phone": "031-556-1400",
      "province": "경기",
      "district": "구리시"
    },
    "branches": [
      {
        "name": "구리(수평)",
        "address": "경기 구리시 이문안로 76",
        "phone": "031-558-2222",
        "district": "구리시"
      },
      {
        "name": "구리(돌다리)",
        "address": "경기 구리시 검배로 23",
        "phone": "031-557-1100",
        "district": "구리시"
      },
      {
        "name": "구리(교문)",
        "address": "경기 구리시 경춘로 174",
        "phone": "031-569-2000",
        "district": "구리시"
      },
      {
        "name": "구리(갈매)",
        "address": "경기 구리시 갈매중앙로 79",
        "phone": "031-551-7000",
        "district": "구리시"
      }
    ]
  },
  "rates": {
    "deposit": {
      "MG더뱅킹정기예금": {
        "3": {
          "r": 1.8,
          "s": "m"
        },
        "6": {
          "r": 2.0,
          "s": "m"
        },
        "12": {
          "r": 3.2,
          "s": "m"
        }
      }
    },
    "saving": {
      "MG더뱅킹정기적금": {
        "12": {
          "r": 2.9,
          "s": "m"
        },
        "6": {
          "r": 0.0,
          "s": "m"
        }
      },
      "MG더뱅킹자유적금": {
        "12": {
          "r": 2.4,
          "s": "m"
        }
      }
    },
    "demand": {
      "온라인자립예탁금": {
        "0": {
          "r": 0.05,
          "s": "w"
        }
      },
      "상상모바일통장": {
        "0": {
          "r": 0.05,
          "s": "m"
        }
      }
    }
  },
  "top_picks": {
    "deposit": {
      "name": "MG더뱅킹정기예금",
      "month": "12",
      "r": 3.2,
      "s": "m"
    },
    "saving": {
      "name": "MG더뱅킹정기적금",
      "month": "12",
      "r": 2.9,
      "s": "m"
    }
  },
  "disclosure_history": [
    {
      "evaluation_date": "20251231",
      "grade": "3",
      "bis_ratio": 11.04,
      "dividend_rate": 1.5
    },
    {
      "evaluation_date": "20250630",
      "grade": "3",
      "bis_ratio": 10.49,
      "dividend_rate": 3.0
    },
    {
      "evaluation_date": "20241231",
      "grade": "2",
      "bis_ratio": 11.77,
      "dividend_rate": 3.0
    },
    {
      "evaluation_date": "20240630",
      "grade": "2",
      "bis_ratio": 10.58,
      "dividend_rate": 4.7
    },
    {
      "evaluation_date": "20231231",
      "grade": "2",
      "bis_ratio": 10.98,
      "dividend_rate": 4.7
    }
  ],
  "nearby_branches": []
}