{
  "updated_at": "2026-04-06T02:58:45+09:00",
  "gmgoCd": "4331",
  "name": "화광",
  "meta": {
    "head_office": {
      "name": "화광(본점)",
      "address": "강원 태백시 장성로 44",
      "phone": "033-581-4312",
      "province": "강원",
      "district": "태백시"
    },
    "branches": [
      {
        "name": "화광(중앙로)",
        "address": "강원 태백시 번영로 354",
        "phone": "033-552-4362",
        "district": "태백시"
      }
    ]
  },
  "rates": {
    "deposit": {},
    "saving": {},
    "demand": {
      "온라인자립예탁금": {
        "0": {
          "r": 0.08,
          "s": "w"
        }
      },
      "상상모바일통장": {
        "0": {
          "r": 0.05,
          "s": "w"
        }
      }
    }
  },
  "top_picks": {
    "deposit": null,
    "saving": null
  },
  "disclosure_history": [
    {
      "evaluation_date": "20251231",
      "grade": "2",
      "bis_ratio": 13.87,
      "dividend_rate": 3.50035
    },
    {
      "evaluation_date": "20250630",
      "grade": "2",
      "bis_ratio": 12.72,
      "dividend_rate": 4.0077
    },
    {
      "evaluation_date": "20241231",
      "grade": "2",
      "bis_ratio": 12.66,
      "dividend_rate": 4.0077
    },
    {
      "evaluation_date": "20240630",
      "grade": "2",
      "bis_ratio": 11.67,
      "dividend_rate": 4.20115
    },
    {
      "evaluation_date": "20231231",
      "grade": "2",
      "bis_ratio": 11.7,
      "dividend_rate": 4.20115
    }
  ],
  "nearby_branches": [
    {
      "gmgoCd": "4344",
      "name": "태백",
      "province": "강원",
      "district": "태백시"
    }
  ]
}