{
  "updated_at": "2026-03-23T17:06:40+09:00",
  "gmgoCd": "4704",
  "name": "문화",
  "meta": {
    "head_office": {
      "name": "문화(본점)",
      "address": "충북 충주시 중앙로 20",
      "phone": "043-848-5510",
      "province": "충북",
      "district": "충주시"
    },
    "branches": [
      {
        "name": "문화(문화)",
        "address": "충북 충주시 중원대로 3377",
        "phone": "043-847-8577",
        "district": "충주시"
      },
      {
        "name": "문화(서충주)",
        "address": "충북 충주시 중앙탑면 원앙9길 10",
        "phone": "043-724-9001",
        "district": "충주시"
      }
    ]
  },
  "rates": {
    "deposit": {
      "MG더뱅킹정기예금": {
        "12": {
          "r": 2.98,
          "s": "m"
        },
        "6": {
          "r": 0.0,
          "s": "m"
        },
        "3": {
          "r": 0.0,
          "s": "m"
        }
      }
    },
    "saving": {
      "MG더뱅킹정기적금": {
        "6": {
          "r": 2.5,
          "s": "m"
        },
        "12": {
          "r": 2.7,
          "s": "m"
        }
      },
      "MG더뱅킹자유적금": {
        "12": {
          "r": 2.6,
          "s": "m"
        }
      }
    },
    "demand": {
      "온라인자립예탁금": {
        "0": {
          "r": 0.1,
          "s": "w"
        }
      },
      "상상모바일통장": {
        "0": {
          "r": 0.1,
          "s": "m"
        }
      }
    }
  },
  "top_picks": {
    "deposit": {
      "name": "MG더뱅킹정기예금",
      "month": "12",
      "r": 2.98,
      "s": "m"
    },
    "saving": {
      "name": "MG더뱅킹정기적금",
      "month": "12",
      "r": 2.7,
      "s": "m"
    }
  },
  "grades_history": [
    {
      "period": "2025_06",
      "grade": "2",
      "bis_ratio": "12.71"
    },
    {
      "period": "2024_12",
      "grade": "2",
      "bis_ratio": "13.64"
    },
    {
      "period": "2024_06",
      "grade": "2",
      "bis_ratio": "13.28"
    },
    {
      "period": "2023_12",
      "grade": "2",
      "bis_ratio": "13.52"
    }
  ],
  "nearby_branches": [
    {
      "gmgoCd": "4701",
      "name": "충주SM",
      "province": "충북",
      "district": "충주시"
    },
    {
      "gmgoCd": "4702",
      "name": "예성",
      "province": "충북",
      "district": "충주시"
    },
    {
      "gmgoCd": "4703",
      "name": "교현",
      "province": "충북",
      "district": "충주시"
    },
    {
      "gmgoCd": "4705",
      "name": "남충주",
      "province": "충북",
      "district": "충주시"
    },
    {
      "gmgoCd": "4707",
      "name": "새충주",
      "province": "충북",
      "district": "충주시"
    }
  ]
}