{
  "updated_at": "2026-04-01T08:58:23+09:00",
  "gmgoCd": "5924",
  "name": "용궁",
  "meta": {
    "head_office": {
      "name": "용궁(본점)",
      "address": "경북 예천군 용궁면 용궁로 111-6",
      "phone": "054-653-7177",
      "province": "경북",
      "district": "예천군"
    },
    "branches": [
      {
        "name": "용궁(범우리)",
        "address": "경북 예천군 호명면 행복로 148",
        "phone": "054-653-8188",
        "district": "예천군"
      }
    ]
  },
  "rates": {
    "deposit": {
      "MG더뱅킹정기예금": {
        "12": {
          "r": 2.6,
          "s": "m"
        }
      }
    },
    "saving": {},
    "demand": {
      "온라인자립예탁금": {
        "0": {
          "r": 0.1,
          "s": "w"
        }
      },
      "상상모바일통장": {
        "0": {
          "r": 0.1,
          "s": "m"
        }
      }
    }
  },
  "top_picks": {
    "deposit": {
      "name": "MG더뱅킹정기예금",
      "month": "12",
      "r": 2.6,
      "s": "m"
    },
    "saving": null
  },
  "grades_history": [
    {
      "period": "2025_12",
      "grade": "2",
      "bis_ratio": "10"
    },
    {
      "period": "2025_06",
      "grade": "2",
      "bis_ratio": "9.47"
    },
    {
      "period": "2024_12",
      "grade": "2",
      "bis_ratio": "10.18"
    },
    {
      "period": "2024_06",
      "grade": "2",
      "bis_ratio": "9.65"
    },
    {
      "period": "2023_12",
      "grade": "2",
      "bis_ratio": "10.64"
    }
  ],
  "nearby_branches": [
    {
      "gmgoCd": "5943",
      "name": "예천군",
      "province": "경북",
      "district": "예천군"
    }
  ]
}