{"updated_at":"2026-04-25T12:30:45.953919","province":"제주","district":"서귀포시","data":[{"gmgoCd":"6708","name":"강정(본점)","province":"제주","district":"서귀포시","disclosure":{"evaluation_date":"20251231","grade":"3","bis_ratio":5.53,"dividend_rate":0.0},"products":{"MG더뱅킹정기예금":{"12":{"r":2.6,"s":"m"}}}},{"gmgoCd":"6710","name":"대포(본점)","province":"제주","district":"서귀포시","disclosure":{"evaluation_date":"20251231","grade":"3","bis_ratio":2.57,"dividend_rate":0.0},"products":{"MG더뱅킹정기예금":{"3":{"r":2.3,"s":"m"},"6":{"r":2.81,"s":"m"},"12":{"r":2.8,"s":"m"}}}},{"gmgoCd":"6734","name":"신례(본점)","province":"제주","district":"서귀포시","disclosure":{"evaluation_date":"20251231","grade":"1","bis_ratio":19.63,"dividend_rate":3.3},"products":{"MG더뱅킹정기예금":{"12":{"r":2.8,"s":"m"},"6":{"r":0.0,"s":"m"},"3":{"r":0.0,"s":"m"}}}},{"gmgoCd":"6735","name":"태흥(본점)","province":"제주","district":"서귀포시","disclosure":{"evaluation_date":"20251231","grade":"3","bis_ratio":12.14,"dividend_rate":2.5},"products":{"MG더뱅킹정기예금":{"12":{"r":2.83,"s":"w"}}}},{"gmgoCd":"6702","name":"서귀포(본점)","province":"제주","district":"서귀포시","disclosure":{"evaluation_date":"20251231","grade":"4","bis_ratio":2.89,"dividend_rate":0.0},"products":{"MG더뱅킹정기예금":{"3":{"r":2.3,"s":"m"},"6":{"r":2.81,"s":"m"},"12":{"r":2.9,"s":"m"}}}},{"gmgoCd":"6713","name":"동홍(본점)","province":"제주","district":"서귀포시","disclosure":{"evaluation_date":"20251231","grade":"3","bis_ratio":5.65,"dividend_rate":0.0},"products":{"MG더뱅킹정기예금":{"12":{"r":2.98,"s":"m"}}}},{"gmgoCd":"6739","name":"의귀(본점)","province":"제주","district":"서귀포시","disclosure":{"evaluation_date":"20251231","grade":"2","bis_ratio":17.41,"dividend_rate":2.50001},"products":{"MG더뱅킹정기예금":{"12":{"r":2.98,"s":"m"},"6":{"r":0.0,"s":"m"},"3":{"r":0.0,"s":"m"}}}},{"gmgoCd":"6741","name":"예래동(본점)","province":"제주","district":"서귀포시","disclosure":{"evaluation_date":"20251231","grade":"3","bis_ratio":7.01,"dividend_rate":0.0},"products":{"MG더뱅킹정기예금":{"3":{"r":2.0,"s":"m"},"6":{"r":2.0,"s":"m"},"12":{"r":3.0,"s":"m"}}}},{"gmgoCd":"6742","name":"서귀포동부(본점)","province":"제주","district":"서귀포시","disclosure":{"evaluation_date":"20251231","grade":"2","bis_ratio":7.89,"dividend_rate":0.0},"products":{"MG더뱅킹정기예금":{"3":{"r":2.3,"s":"m"},"6":{"r":2.5,"s":"m"},"12":{"r":3.0,"s":"m"}}}},{"gmgoCd":"6707","name":"호근(본점)","province":"제주","district":"서귀포시","disclosure":{"evaluation_date":"20251231","grade":"2","bis_ratio":11.01,"dividend_rate":3.03},"products":{"MG더뱅킹정기예금":{"12":{"r":3.0,"s":"w"}}}},{"gmgoCd":"6706","name":"서호(본점)","province":"제주","district":"서귀포시","disclosure":{"evaluation_date":"20251231","grade":"3","bis_ratio":7.02,"dividend_rate":0.0},"products":{"MG더뱅킹정기예금":{"3":{"r":2.6,"s":"m"},"6":{"r":2.6,"s":"m"},"12":{"r":3.09,"s":"m"}}}},{"gmgoCd":"6733","name":"제주남원동부(본점)","province":"제주","district":"서귀포시","disclosure":{"evaluation_date":"20251231","grade":"3","bis_ratio":11.15,"dividend_rate":0.0},"products":{"MG더뱅킹정기예금":{"12":{"r":3.09,"s":"m"},"6":{"r":0.0,"s":"m"},"3":{"r":0.0,"s":"m"}}}},{"gmgoCd":"6716","name":"산남(본점)","province":"제주","district":"서귀포시","disclosure":{"evaluation_date":"20251231","grade":"2","bis_ratio":12.74,"dividend_rate":3.0},"products":{"MG더뱅킹정기예금":{"3":{"r":2.3,"s":"m"},"6":{"r":2.6,"s":"m"},"12":{"r":3.09,"s":"m"}}}},{"gmgoCd":"6705","name":"법환(본점)","province":"제주","district":"서귀포시","disclosure":{"evaluation_date":"20251231","grade":"2","bis_ratio":13.76,"dividend_rate":3.0},"products":{"MG더뱅킹정기예금":{"12":{"r":3.09,"s":"m"}}}},{"gmgoCd":"6711","name":"하원(본점)","province":"제주","district":"서귀포시","disclosure":{"evaluation_date":"20251231","grade":"3","bis_ratio":5.9,"dividend_rate":0.0},"products":{"MG더뱅킹정기예금":{"3":{"r":2.3,"s":"m"},"6":{"r":2.6,"s":"m"},"12":{"r":3.5,"s":"m"}}}},{"gmgoCd":"6704","name":"서홍(본점)","province":"제주","district":"서귀포시","disclosure":{"evaluation_date":"20251231","grade":"3","bis_ratio":2.48,"dividend_rate":0.0},"products":{"MG더뱅킹정기예금":{"12":{"r":3.6,"s":"w"}}}}]}