{
  "updated_at": "2026-04-01T03:16:23+09:00",
  "gmgoCd": "2823",
  "name": "강진완도",
  "meta": {
    "head_office": {
      "name": "강진완도(본점)",
      "address": "전남 강진군 강진읍 중앙로 137",
      "phone": "061-433-1988",
      "province": "전남",
      "district": "강진군"
    },
    "branches": [
      {
        "name": "강진완도(완도)",
        "address": "전남 완도군 완도읍 장보고대로 189",
        "phone": "061-554-4811",
        "district": "완도군"
      }
    ]
  },
  "rates": {
    "deposit": {
      "MG더뱅킹정기예금": {
        "12": {
          "r": 2.5,
          "s": "w"
        }
      }
    },
    "saving": {},
    "demand": {
      "온라인자립예탁금": {
        "0": {
          "r": 0.1,
          "s": "w"
        }
      },
      "상상모바일통장": {
        "0": {
          "r": 0.1,
          "s": "w"
        }
      }
    }
  },
  "top_picks": {
    "deposit": {
      "name": "MG더뱅킹정기예금",
      "month": "12",
      "r": 2.5,
      "s": "w"
    },
    "saving": null
  },
  "grades_history": [],
  "nearby_branches": []
}